{
  "initialPrice": 116612,
  "history": [
    {
      "price": 116612,
      "timestamp": "2025-07-25T11:45:44Z"
    },
    {
      "price": 116608,
      "timestamp": "2025-07-25T11:51:42Z"
    },
    {
      "price": 116178,
      "timestamp": "2025-07-25T12:41:04Z"
    },
    {
      "price": 116172,
      "timestamp": "2025-07-25T12:44:18Z"
    },
    {
      "price": 115842,
      "timestamp": "2025-07-25T13:49:07Z"
    },
    {
      "price": 115990,
      "timestamp": "2025-07-25T14:09:46Z"
    },
    {
      "price": 115661,
      "timestamp": "2025-07-25T14:28:49Z"
    },
    {
      "price": 115217,
      "timestamp": "2025-07-25T14:48:06Z"
    },
    {
      "price": 115228,
      "timestamp": "2025-07-25T14:54:01Z"
    },
    {
      "price": 115111,
      "timestamp": "2025-07-25T15:01:14Z"
    },
    {
      "price": 115304,
      "timestamp": "2025-07-25T15:19:26Z"
    },
    {
      "price": 115334,
      "timestamp": "2025-07-25T15:22:00Z"
    },
    {
      "price": 115429,
      "timestamp": "2025-07-25T15:44:05Z"
    },
    {
      "price": 115675,
      "timestamp": "2025-07-25T15:58:32Z"
    },
    {
      "price": 115999,
      "timestamp": "2025-07-25T16:55:04Z"
    },
    {
      "price": 116142,
      "timestamp": "2025-07-25T17:46:01Z"
    },
    {
      "price": 116500,
      "timestamp": "2025-07-25T18:57:01Z"
    },
    {
      "price": 116646,
      "timestamp": "2025-07-25T19:31:22Z"
    },
    {
      "price": 116883,
      "timestamp": "2025-07-25T19:52:44Z"
    },
    {
      "price": 116990,
      "timestamp": "2025-07-25T20:43:32Z"
    },
    {
      "price": 117143,
      "timestamp": "2025-07-25T20:57:54Z"
    },
    {
      "price": 117199,
      "timestamp": "2025-07-25T21:37:41Z"
    },
    {
      "price": 117169,
      "timestamp": "2025-07-25T21:52:34Z"
    },
    {
      "price": 117325,
      "timestamp": "2025-07-25T22:48:19Z"
    },
    {
      "price": 117372,
      "timestamp": "2025-07-25T23:37:48Z"
    },
    {
      "price": 117543,
      "timestamp": "2025-07-25T23:53:20Z"
    },
    {
      "price": 117553,
      "timestamp": "2025-07-26T03:48:40Z"
    },
    {
      "price": 117502,
      "timestamp": "2025-07-26T05:01:02Z"
    },
    {
      "price": 117507,
      "timestamp": "2025-07-26T05:50:38Z"
    },
    {
      "price": 117409,
      "timestamp": "2025-07-26T06:56:10Z"
    },
    {
      "price": 117376,
      "timestamp": "2025-07-26T07:36:10Z"
    },
    {
      "price": 117379,
      "timestamp": "2025-07-26T07:51:33Z"
    },
    {
      "price": 117519,
      "timestamp": "2025-07-26T08:50:35Z"
    },
    {
      "price": 117499,
      "timestamp": "2025-07-26T09:38:03Z"
    },
    {
      "price": 117550,
      "timestamp": "2025-07-26T09:51:28Z"
    },
    {
      "price": 117996,
      "timestamp": "2025-07-26T10:45:11Z"
    },
    {
      "price": 117972,
      "timestamp": "2025-07-26T11:31:07Z"
    },
    {
      "price": 117864,
      "timestamp": "2025-07-26T11:51:49Z"
    },
    {
      "price": 118185,
      "timestamp": "2025-07-26T13:43:15Z"
    },
    {
      "price": 118191,
      "timestamp": "2025-07-26T13:56:44Z"
    },
    {
      "price": 118062,
      "timestamp": "2025-07-26T14:42:31Z"
    },
    {
      "price": 118178,
      "timestamp": "2025-07-26T14:55:19Z"
    },
    {
      "price": 117961,
      "timestamp": "2025-07-26T15:42:09Z"
    },
    {
      "price": 118089,
      "timestamp": "2025-07-26T15:58:19Z"
    },
    {
      "price": 118080,
      "timestamp": "2025-07-26T16:52:20Z"
    },
    {
      "price": 118049,
      "timestamp": "2025-07-26T17:42:17Z"
    },
    {
      "price": 118042,
      "timestamp": "2025-07-26T17:53:38Z"
    },
    {
      "price": 118122,
      "timestamp": "2025-07-26T18:55:40Z"
    },
    {
      "price": 118115,
      "timestamp": "2025-07-26T19:28:11Z"
    },
    {
      "price": 118133,
      "timestamp": "2025-07-26T19:44:32Z"
    },
    {
      "price": 118276,
      "timestamp": "2025-07-26T19:55:46Z"
    },
    {
      "price": 117988,
      "timestamp": "2025-07-26T20:40:13Z"
    },
    {
      "price": 118005,
      "timestamp": "2025-07-26T20:54:13Z"
    },
    {
      "price": 117987,
      "timestamp": "2025-07-26T21:34:31Z"
    },
    {
      "price": 118001,
      "timestamp": "2025-07-26T21:53:30Z"
    },
    {
      "price": 118055,
      "timestamp": "2025-07-26T22:42:40Z"
    },
    {
      "price": 118104,
      "timestamp": "2025-07-26T22:55:04Z"
    },
    {
      "price": 117993,
      "timestamp": "2025-07-26T23:37:23Z"
    },
    {
      "price": 117972,
      "timestamp": "2025-07-26T23:52:51Z"
    },
    {
      "price": 118236,
      "timestamp": "2025-07-27T04:10:58Z"
    },
    {
      "price": 118296,
      "timestamp": "2025-07-27T05:42:50Z"
    },
    {
      "price": 118263,
      "timestamp": "2025-07-27T05:58:03Z"
    },
    {
      "price": 118331,
      "timestamp": "2025-07-27T06:57:44Z"
    },
    {
      "price": 118191,
      "timestamp": "2025-07-27T07:35:27Z"
    },
    {
      "price": 118192,
      "timestamp": "2025-07-27T07:51:49Z"
    },
    {
      "price": 118070,
      "timestamp": "2025-07-27T08:50:53Z"
    },
    {
      "price": 117925,
      "timestamp": "2025-07-27T09:39:24Z"
    },
    {
      "price": 117921,
      "timestamp": "2025-07-27T09:54:22Z"
    },
    {
      "price": 118234,
      "timestamp": "2025-07-27T10:46:49Z"
    },
    {
      "price": 118238,
      "timestamp": "2025-07-27T11:30:25Z"
    },
    {
      "price": 118139,
      "timestamp": "2025-07-27T11:51:28Z"
    },
    {
      "price": 118182,
      "timestamp": "2025-07-27T13:41:24Z"
    },
    {
      "price": 118199,
      "timestamp": "2025-07-27T13:55:48Z"
    },
    {
      "price": 118432,
      "timestamp": "2025-07-27T14:40:54Z"
    },
    {
      "price": 118342,
      "timestamp": "2025-07-27T14:53:23Z"
    },
    {
      "price": 118430,
      "timestamp": "2025-07-27T15:38:33Z"
    },
    {
      "price": 118468,
      "timestamp": "2025-07-27T15:53:07Z"
    },
    {
      "price": 119449,
      "timestamp": "2025-07-27T16:50:49Z"
    },
    {
      "price": 119126,
      "timestamp": "2025-07-27T17:41:44Z"
    },
    {
      "price": 119171,
      "timestamp": "2025-07-27T17:55:16Z"
    },
    {
      "price": 119061,
      "timestamp": "2025-07-27T18:56:14Z"
    },
    {
      "price": 118965,
      "timestamp": "2025-07-27T19:30:16Z"
    },
    {
      "price": 119031,
      "timestamp": "2025-07-27T19:45:43Z"
    },
    {
      "price": 118917,
      "timestamp": "2025-07-27T20:41:38Z"
    },
    {
      "price": 118915,
      "timestamp": "2025-07-27T20:55:36Z"
    },
    {
      "price": 119023,
      "timestamp": "2025-07-27T21:35:42Z"
    },
    {
      "price": 119138,
      "timestamp": "2025-07-27T21:51:29Z"
    },
    {
      "price": 119732,
      "timestamp": "2025-07-27T22:45:56Z"
    },
    {
      "price": 119409,
      "timestamp": "2025-07-27T23:39:19Z"
    },
    {
      "price": 119419,
      "timestamp": "2025-07-27T23:54:16Z"
    },
    {
      "price": 119384,
      "timestamp": "2025-07-28T04:11:04Z"
    },
    {
      "price": 119459,
      "timestamp": "2025-07-28T05:46:55Z"
    },
    {
      "price": 119454,
      "timestamp": "2025-07-28T07:01:43Z"
    },
    {
      "price": 118942,
      "timestamp": "2025-07-28T07:49:01Z"
    },
    {
      "price": 118991,
      "timestamp": "2025-07-28T08:59:07Z"
    },
    {
      "price": 118803,
      "timestamp": "2025-07-28T09:52:26Z"
    },
    {
      "price": 118752,
      "timestamp": "2025-07-28T10:52:49Z"
    },
    {
      "price": 118580,
      "timestamp": "2025-07-28T11:35:52Z"
    },
    {
      "price": 118773,
      "timestamp": "2025-07-28T11:52:08Z"
    },
    {
      "price": 118551,
      "timestamp": "2025-07-28T13:53:42Z"
    },
    {
      "price": 118142,
      "timestamp": "2025-07-28T14:52:59Z"
    },
    {
      "price": 118266,
      "timestamp": "2025-07-28T15:47:45Z"
    },
    {
      "price": 118147,
      "timestamp": "2025-07-28T16:58:38Z"
    },
    {
      "price": 117873,
      "timestamp": "2025-07-28T17:47:07Z"
    },
    {
      "price": 117805,
      "timestamp": "2025-07-28T18:59:14Z"
    },
    {
      "price": 118079,
      "timestamp": "2025-07-28T19:34:19Z"
    },
    {
      "price": 117690,
      "timestamp": "2025-07-28T19:52:28Z"
    },
    {
      "price": 117864,
      "timestamp": "2025-07-28T20:47:14Z"
    },
    {
      "price": 118126,
      "timestamp": "2025-07-28T21:37:20Z"
    },
    {
      "price": 118252,
      "timestamp": "2025-07-28T21:52:26Z"
    },
    {
      "price": 117863,
      "timestamp": "2025-07-28T22:51:29Z"
    },
    {
      "price": 118093,
      "timestamp": "2025-07-28T23:43:24Z"
    },
    {
      "price": 117992,
      "timestamp": "2025-07-28T23:57:52Z"
    },
    {
      "price": 118700,
      "timestamp": "2025-07-29T04:13:28Z"
    },
    {
      "price": 118723,
      "timestamp": "2025-07-29T05:47:15Z"
    },
    {
      "price": 118869,
      "timestamp": "2025-07-29T07:00:38Z"
    },
    {
      "price": 118960,
      "timestamp": "2025-07-29T07:48:48Z"
    },
    {
      "price": 118876,
      "timestamp": "2025-07-29T08:58:29Z"
    },
    {
      "price": 118869,
      "timestamp": "2025-07-29T09:51:31Z"
    },
    {
      "price": 118450,
      "timestamp": "2025-07-29T10:52:20Z"
    },
    {
      "price": 118494,
      "timestamp": "2025-07-29T11:34:27Z"
    },
    {
      "price": 118433,
      "timestamp": "2025-07-29T11:52:50Z"
    },
    {
      "price": 118741,
      "timestamp": "2025-07-29T13:54:19Z"
    },
    {
      "price": 117992,
      "timestamp": "2025-07-29T14:56:03Z"
    },
    {
      "price": 117448,
      "timestamp": "2025-07-29T15:50:28Z"
    },
    {
      "price": 117664,
      "timestamp": "2025-07-29T16:58:12Z"
    },
    {
      "price": 117757,
      "timestamp": "2025-07-29T17:50:20Z"
    },
    {
      "price": 117602,
      "timestamp": "2025-07-29T19:00:31Z"
    },
    {
      "price": 117451,
      "timestamp": "2025-07-29T19:41:50Z"
    },
    {
      "price": 117557,
      "timestamp": "2025-07-29T19:53:31Z"
    },
    {
      "price": 117168,
      "timestamp": "2025-07-29T20:47:41Z"
    },
    {
      "price": 117302,
      "timestamp": "2025-07-29T21:39:48Z"
    },
    {
      "price": 117397,
      "timestamp": "2025-07-29T21:54:05Z"
    },
    {
      "price": 117741,
      "timestamp": "2025-07-29T22:48:24Z"
    },
    {
      "price": 117928,
      "timestamp": "2025-07-29T23:39:08Z"
    },
    {
      "price": 117784,
      "timestamp": "2025-07-29T23:54:07Z"
    },
    {
      "price": 118142,
      "timestamp": "2025-07-30T03:57:38Z"
    },
    {
      "price": 117916,
      "timestamp": "2025-07-30T05:47:26Z"
    },
    {
      "price": 118281,
      "timestamp": "2025-07-30T07:02:27Z"
    },
    {
      "price": 118193,
      "timestamp": "2025-07-30T07:50:35Z"
    },
    {
      "price": 118421,
      "timestamp": "2025-07-30T08:59:48Z"
    },
    {
      "price": 118063,
      "timestamp": "2025-07-30T09:53:33Z"
    },
    {
      "price": 118370,
      "timestamp": "2025-07-30T10:51:45Z"
    },
    {
      "price": 117882,
      "timestamp": "2025-07-30T11:35:24Z"
    },
    {
      "price": 117759,
      "timestamp": "2025-07-30T11:52:51Z"
    },
    {
      "price": 117588,
      "timestamp": "2025-07-30T13:53:52Z"
    },
    {
      "price": 118104,
      "timestamp": "2025-07-30T14:51:04Z"
    },
    {
      "price": 118132,
      "timestamp": "2025-07-30T15:48:34Z"
    },
    {
      "price": 117787,
      "timestamp": "2025-07-30T16:56:34Z"
    },
    {
      "price": 117804,
      "timestamp": "2025-07-30T17:48:39Z"
    },
    {
      "price": 116747,
      "timestamp": "2025-07-30T19:00:14Z"
    }
  ]
}
